LICENSE
README.md
setup.py
nonebot_plugin_ygo_trade/__init__.py
nonebot_plugin_ygo_trade.egg-info/PKG-INFO
nonebot_plugin_ygo_trade.egg-info/SOURCES.txt
nonebot_plugin_ygo_trade.egg-info/dependency_links.txt
nonebot_plugin_ygo_trade.egg-info/requires.txt
nonebot_plugin_ygo_trade.egg-info/top_level.txt