Metadata-Version: 2.1
Name: nonebot-plugin-ygo-trade
Version: 1.0.0
Summary: nonebot的游戏王查价插件
Home-page: https://github.com/Kaguyaya/nonebot_plugin_ygotrade
Author: kaguya
Author-email: 467241156@qq.com
Maintainer: kaguya
Maintainer-email: 467241156@qq.com
License: UNKNOWN
Platform: all
License-File: LICENSE
